{"0": "Melbourne Renegades", "1": "Australia Under-19s", "2": "Adelaide Strikers", "3": "Australia", "4": "Australia", "5": "Adelaide Strikers", "6": "Australia", "7": "Australia", "8": "Adelaide Strikers", "9": "Australia", "10": "Brisbane Heat", "11": "Australian Institute of Sport", "12": "Brisbane Heat", "13": "Australia", "14": "Australia Under-19s", "15": "Australia", "16": "Australia", "17": "Australia", "18": "Australia", "19": "Australia", "20": "Australia", "21": "Australia Under-19s", "22": "Hobart Hurricanes", "23": "Denmark", "24": "Australia", "25": "Australia", "26": "Australia", "27": "Australian Capital Territory", "28": "Australia", "29": "Australia", "30": "Australia", "31": "Kingborough", "32": "Melbourne Renegades", "33": "Australia A", "34": "Australia", "35": "Brisbane Heat", "36": "Kings XI Punjab", "37": "Brisbane Heat", "38": "Australia", "39": "Australia", "40": "Adelaide Strikers", "41": "Australia", "42": "Australia Under-19s", "43": "Australia", "44": "United States of America", "45": "Australia", "46": "Adelaide Strikers", "47": "Australia", "48": "Derbyshire 2nd XI", "49": "Australia", "50": "South Australia", "51": "Australian Universities", "52": "Australia Under-19s", "53": "Queensland", "54": "Melbourne Renegades", "55": "Australia", "56": "Australia", "57": "Australia Under-19s", "58": "Queensland", "59": "Adelaide Strikers", "60": "Australia A", "61": "Australia", "62": "Australia", "63": "Adelaide Strikers", "64": "New South Wales", "65": "Adelaide Strikers", "66": "Australia", "67": "England", "68": "Australia", "69": "Adelaide Strikers", "70": "Cricket Australia Invitation XI", "71": "Australia", "72": "Australian Capital Territory", "73": "Australia", "74": "Australia", "75": "Australia", "76": "Australia", "77": "Hobart Hurricanes", "78": "Australia", "79": "Australia", "80": "Australia", "81": "Adelaide Strikers", "82": "Adelaide Strikers", "83": "Australian Capital Territory", "84": "Australia", "85": "Brisbane Heat", "86": "United States of America", "87": "Australia Under-19s", "88": "Adelaide Strikers", "89": "Australia", "90": "Adelaide Strikers", "91": "Australia", "92": "Australia Under-19s", "93": "Australia Centre of Excellence", "94": "Australia Under-19s", "95": "Australia A", "96": "Australia Under-19s", "97": "Adelaide Strikers", "98": "Adelaide Strikers", "99": "Australia Under-19s", "100": "Australia", "101": "Australia", "102": "Australia", "103": "Australia", "104": "Australia", "105": "Hobart Hurricanes", "106": "Melbourne Renegades", "107": "Australia Under-19s", "108": "Australia", "109": "Australia", "110": "New South Wales", "111": "Australia Under-19s", "112": "Australia Under-19s", "113": "Australia", "114": "Hobart Hurricanes", "115": "Australia", "116": "South Africa", "117": "Adelaide Strikers", "118": "Australia", "119": "Australia", "120": "New South Wales Under-19s", "121": "Australia", "122": "Australia", "123": "Australia", "124": "Australia Under-19s", "125": "Barbados Tridents", "126": "Australia", "127": "Australia", "128": "Melbourne Stars", "129": "Brisbane Heat", "130": "Australia Under-19s", "131": "Australia Under-19s", "132": "Beenleigh-Logan", "133": "Adelaide Strikers", "134": "Australia Under-19s", "135": "Western Australia", "136": "Australia", "137": "New Zealand", "138": "Australia Under-19s", "139": "Australia", "140": "Hampshire 2nd XI", "141": "Australia", "142": "Cricket Australia XI", "143": "Australia", "144": "Australia", "145": "Kolkata Knight Riders", "146": "Australia", "147": "Leicestershire", "148": "England", "149": "Australia Under-19s", "150": "Western Australia", "151": "Australia", "152": "Adelaide Strikers", "153": "Australian Capital Territory", "154": "Australia Under-19s", "155": "Australia", "156": "Australia Under-19s", "157": "Australia", "158": "Australia", "159": "Glamorgan", "160": "Hampshire 2nd XI", "161": "Australia", "162": "Australia", "163": "Australia", "164": "Australia", "165": "Netherlands", "166": "Australia", "167": "Middlesex 2nd XI", "168": "Australia", "169": "Australia", "170": "Australia Under-19s", "171": "Australia", "172": "Australia", "173": "Australia", "174": "Australia", "175": "Auckland", "176": "Australia", "177": "Australia Under-19s", "178": "Kings XI Punjab", "179": "Adelaide Strikers", "180": "Australia", "181": "Ireland", "182": "Adelaide Strikers", "183": "Australia Under-19s", "184": "Australia", "185": "Australia", "186": "Australia", "187": "Adelaide Strikers", "188": "Australia", "189": "Australia", "190": "Australia", "191": "Australia", "192": "Australia", "193": "Australia", "194": "Australia", "195": "Australia", "196": "Australia A", "197": "Adelaide Strikers", "198": "South Australia", "199": "Elite International Cricket Academy", "200": "Brisbane Heat", "201": "Australian Capital Territory", "202": "Australia", "203": "Australia Under-19s", "204": "Hobart Hurricanes", "205": "Victoria", "206": "Australia", "207": "Australia Under-19s", "208": "Australia A", "209": "Australian Universities", "210": "Australia", "211": "Australia", "212": "Australia Centre of Excellence", "213": "Australia Under-19s", "214": "Australia", "215": "Australia", "216": "Victoria", "217": "Australia", "218": "Brisbane Heat", "219": "Leicestershire 2nd XI", "220": "Australia", "221": "New South Wales Second XI", "222": "Australia", "223": "Australia Under-19s", "224": "South Australia", "225": "Adelaide Strikers", "226": "New South Wales", "227": "Adelaide Strikers", "228": "Netherlands", "229": "Australia", "230": "Australia Under-19s", "231": "South Australia", "232": "Netherlands", "233": "Australian Capital Territory Under-23s", "234": "Australia Under-19s", "235": "Australia", "236": "Australia", "237": "Australia", "238": "Australia", "239": "Pakistan", "240": "Australia", "241": "Australia", "242": "Australia Under-19s", "243": "Hobart Hurricanes", "244": "Australia Under-19s", "245": "New Zealand", "246": "Australia Under-19s", "247": "Australia"}